Workbook
Name BackorderCost: Scenario!$F$18
Name BeginInv: Scenario!$F$6
Name BottlesPerHour: Scenario!$F$11
Name DaysPerMonth: Scenario!$F$13
Name EndTarget: Scenario!$F$8
Name HireCost: Scenario!$F$15
Name HoldCost: Scenario!$F$17
Name HoursPerDay: Scenario!$F$12
Name LaborCost: Scenario!$F$14
Name LayoffCost: Scenario!$F$16
Name MaxInventory: Scenario!$F$9
Name OTCost: Scenario!$F$20
Name OTLimitPct: Scenario!$F$19
Name SafetyStock: Scenario!$F$7
Name StartWorkers: Scenario!$F$10
Name SubCapacity: Scenario!$F$22
Name SubCost: Scenario!$F$21

Sheet Start Here
B1: Aggregate Anxiety: Aggregate Planning in Excel
B2: Juicetification Inc. — aggregate production planning, built by you in Excel.
B4: Student name | C4: Test Student | D4: This workbook was made for you: your demand and numbers differ from your classmates'. Upload only your own file.
B5: Student ID | C5: S1
B6: Scenario number | C6: 7
B8: How this works
B9: Pieces | C9: You build and submit this workbook one piece at a time in the app: the chase plan, then the level plan, then the hybrid plan, then the comparison on the Summary sheet.
B10: Design it | C10: On each plan sheet only Month and Demand are given. YOU decide which columns the plan needs: type a heading in row 1 for each one (peach cells), then the formulas for January–December below it, and the yearly totals in row 14.
B11: Plan first | C11: Fill the planning cells under the grid first — the one-off numbers the months will use.
B12: Use formulas | C12: Every number you work out must be an Excel formula (start with =). Use the names on the Scenario sheet, e.g. =…*LaborCost.
B13: Check | C13: Save as .xlsx and upload it at that piece's step in the app. You'll see which cells are right; each new attempt unlocks more help on what is still wrong. When a piece is all correct, submit it and move on.
B15: Colour key
C16: Given data — do not change
C17: Your column heading goes here (row 1)
C18: Your formula goes here
C19: Yearly totals row (row 14)
B21: Your company's policy
B22: Your company carries no safety stock: the chase plan uses up the beginning inventory in January and then ends each month with 0 bottles; the level plan aims to end December at 0.
B24: Questions every plan must answer, for each month
B25: 1. | C25: How many bottles are on the shelf when the month starts?
B26: 2. | C26: How many customer orders are still waiting from earlier months?
B27: 3. | C27: How many bottles will you make this month?
B28: 4. | C28: How many workers do you employ this month?
B29: 5. | C29: How many workers did you add this month?
B30: 6. | C30: How many workers did you let go this month?
B31: 7. | C31: How many bottles are left on the shelf at the end of the month?
B32: 8. | C32: How many orders are still unfilled at the end of the month?
B33: 9. | C33: What did your workforce cost this month?
B34: 10. | C34: What did hiring cost this month?
B35: 11. | C35: What did layoffs cost this month?
B36: 12. | C36: What did it cost to keep stock this month?
... B38: 14. | C38: What did the whole month cost?
B40: Each question becomes a column. Which columns does each one depend on? That is your formula.
B41: Stuck on Excel itself? See the Excel Help sheet.

Sheet Scenario
A1: Scenario: your given data
A2: Use the Excel NAMES in column G in your formulas, e.g. =F2*LaborCost. Never retype these numbers.
A4: Demand forecast | E4: Given data and their Excel names
A5: Month | B5: Demand (bottles) | E5: Given data | F5: Value | G5: Excel name | H5: Unit
A6: January | B6: 7000 | E6: Inventory on hand before January | F6: 2400 | G6: BeginInv | H6: bottles
A7: February | B7: 6000 | E7: Safety-stock quantity | F7: 2400 | G7: SafetyStock | H7: bottles
A8: March | B8: 7000 | E8: Inventory each chase month aims to end with (and the level plan's December target) | F8: 0 | G8: EndTarget | H8: bottles
A9: April | B9: 11500 | E9: Storage capacity (most bottles you can hold) | F9: 30000 | G9: MaxInventory | H9: bottles
A10: May | B10: 13000 | E10: Workers employed before January | F10: 8 | G10: StartWorkers | H10: workers
A11: June | B11: 16500 | E11: Output of one worker per hour | F11: 5 | G11: BottlesPerHour | H11: bottles/hour
A12: July | B12: 18500 | E12: Paid hours per worker per day | F12: 8 | G12: HoursPerDay | H12: hours/day
A13: August | B13: 14000 | E13: Working days per month | F13: 25 | G13: DaysPerMonth | H13: days/month
A14: September | B14: 10500 | E14: Regular labor cost per worker per month | F14: 3200 | G14: LaborCost | H14: $/worker/month
A15: October | B15: 9000 | E15: Cost to hire one worker | F15: 600 | G15: HireCost | H15: $/worker
A16: November | B16: 7000 | E16: Cost to lay off one worker | F16: 900 | G16: LayoffCost | H16: $/worker
A17: December | B17: 6000 | E17: Cost to hold one bottle for one month | F17: 0.25 | G17: HoldCost | H17: $/bottle/month
E18: Cost of one bottle backordered for one month | F18: 1.5 | G18: BackorderCost | H18: $/bottle/month
E19: Overtime limit as a share of regular capacity | F19: 0.2 | G19: OTLimitPct | H19: fraction
E20: Overtime cost per bottle (extra, on top of labor) | F20: 4.5 | G20: OTCost | H20: $/bottle
E21: Subcontracting cost per bottle | F21: 5.25 | G21: SubCost | H21: $/bottle
E22: Most bottles you can subcontract per month | F22: 5000 | G22: SubCapacity | H22: bottles/month

Sheet Chase Plan
A1: Month | B1: Demand | C1: Starting Stock | D1: Backlog Carried In | E1: Bottles Made | F1: Crew | G1: Regular Capacity | H1: New Hires | I1: Fired | J1: Unfilled Orders | K1: Closing Stock | L1: Wages | M1: Storage Cost | N1: Shortage Penalty | O1: Hiring Expense | P1: Severance | Q1: Monthly Total Cost
A2: January | B2: 7000 | C2: =BeginInv -> 2400 | D2: =0 -> 0 | E2: =MAX(0,B2+$C$18-C2+D2) -> 4600 | F2: =ROUNDUP(E2/$C$17,0) -> 5 | G2: =F2*$C$17 -> 5000 | H2: =MAX(0,F2-StartWorkers) -> 0 | I2: =MAX(0,StartWorkers-F2) -> 3 | J2: =MAX(0,B2+D2-C2-E2) -> 0 | K2: =MAX(0,C2+E2-D2-B2) -> 0 | L2: =F2*LaborCost -> 16000 | M2: =K2*HoldCost -> 0 | N2: =J2*BackorderCost -> 0 | O2: =H2*HireCost -> 0 | P2: =I2*LayoffCost -> 2700 | Q2: =L2+O2+P2+M2+N2 -> 18700
A3: February | B3: 6000 | C3: =K2 -> 0 | D3: =J2 -> 0 | E3: =MAX(0,B3+$C$18-C3+D3) -> 6000 | F3: =ROUNDUP(E3/$C$17,0) -> 6 | G3: =F3*$C$17 -> 6000 | H3: =MAX(0,F3-F2) -> 1 | I3: =MAX(0,F2-F3) -> 0 | J3: =MAX(0,B3+D3-C3-E3) -> 0 | K3: =MAX(0,C3+E3-D3-B3) -> 0 | L3: =F3*LaborCost -> 19200 | M3: =K3*HoldCost -> 0 | N3: =J3*BackorderCost -> 0 | O3: =H3*HireCost -> 600 | P3: =I3*LayoffCost -> 0 | Q3: =L3+O3+P3+M3+N3 -> 19800
A4: March | B4: 7000 | C4: =K3 -> 0 | D4: =J3 -> 0 | E4: =MAX(0,B4+$C$18-C4+D4) -> 7000 | F4: =ROUNDUP(E4/$C$17,0) -> 7 | G4: =F4*$C$17 -> 7000 | H4: =MAX(0,F4-F3) -> 1 | I4: =MAX(0,F3-F4) -> 0 | J4: =MAX(0,B4+D4-C4-E4) -> 0 | K4: =MAX(0,C4+E4-D4-B4) -> 0 | L4: =F4*LaborCost -> 22400 | M4: =K4*HoldCost -> 0 | N4: =J4*BackorderCost -> 0 | O4: =H4*HireCost -> 600 | P4: =I4*LayoffCost -> 0 | Q4: =L4+O4+P4+M4+N4 -> 23000
A5: April | B5: 11500 | C5: =K4 -> 0 | D5: =J4 -> 0 | E5: =MAX(0,B5+$C$18-C5+D5) -> 11500 | F5: =ROUNDUP(E5/$C$17,0) -> 12 | G5: =F5*$C$17 -> 12000 | H5: =MAX(0,F5-F4) -> 5 | I5: =MAX(0,F4-F5) -> 0 | J5: =MAX(0,B5+D5-C5-E5) -> 0 | K5: =MAX(0,C5+E5-D5-B5) -> 0 | L5: =F5*LaborCost -> 38400 | M5: =K5*HoldCost -> 0 | N5: =J5*BackorderCost -> 0 | O5: =H5*HireCost -> 3000 | P5: =I5*LayoffCost -> 0 | Q5: =L5+O5+P5+M5+N5 -> 41400
A6: May | B6: 13000 | C6: =K5 -> 0 | D6: =J5 -> 0 | E6: =MAX(0,B6+$C$18-C6+D6) -> 13000 | F6: =ROUNDUP(E6/$C$17,0) -> 13 | G6: =F6*$C$17 -> 13000 | H6: =MAX(0,F6-F5) -> 1 | I6: =MAX(0,F5-F6) -> 0 | J6: =MAX(0,B6+D6-C6-E6) -> 0 | K6: =MAX(0,C6+E6-D6-B6) -> 0 | L6: =F6*LaborCost -> 41600 | M6: =K6*HoldCost -> 0 | N6: =J6*BackorderCost -> 0 | O6: =H6*HireCost -> 600 | P6: =I6*LayoffCost -> 0 | Q6: =L6+O6+P6+M6+N6 -> 42200
A7: June | B7: 16500 | C7: =K6 -> 0 | D7: =J6 -> 0 | E7: =MAX(0,B7+$C$18-C7+D7) -> 16500 | F7: =ROUNDUP(E7/$C$17,0) -> 17 | G7: =F7*$C$17 -> 17000 | H7: =MAX(0,F7-F6) -> 4 | I7: =MAX(0,F6-F7) -> 0 | J7: =MAX(0,B7+D7-C7-E7) -> 0 | K7: =MAX(0,C7+E7-D7-B7) -> 0 | L7: =F7*LaborCost -> 54400 | M7: =K7*HoldCost -> 0 | N7: =J7*BackorderCost -> 0 | O7: =H7*HireCost -> 2400 | P7: =I7*LayoffCost -> 0 | Q7: =L7+O7+P7+M7+N7 -> 56800
A8: July | B8: 18500 | C8: =K7 -> 0 | D8: =J7 -> 0 | E8: =MAX(0,B8+$C$18-C8+D8) -> 18500 | F8: =ROUNDUP(E8/$C$17,0) -> 19 | G8: =F8*$C$17 -> 19000 | H8: =MAX(0,F8-F7) -> 2 | I8: =MAX(0,F7-F8) -> 0 | J8: =MAX(0,B8+D8-C8-E8) -> 0 | K8: =MAX(0,C8+E8-D8-B8) -> 0 | L8: =F8*LaborCost -> 60800 | M8: =K8*HoldCost -> 0 | N8: =J8*BackorderCost -> 0 | O8: =H8*HireCost -> 1200 | P8: =I8*LayoffCost -> 0 | Q8: =L8+O8+P8+M8+N8 -> 62000
A9: August | B9: 14000 | C9: =K8 -> 0 | D9: =J8 -> 0 | E9: =MAX(0,B9+$C$18-C9+D9) -> 14000 | F9: =ROUNDUP(E9/$C$17,0) -> 14 | G9: =F9*$C$17 -> 14000 | H9: =MAX(0,F9-F8) -> 0 | I9: =MAX(0,F8-F9) -> 5 | J9: =MAX(0,B9+D9-C9-E9) -> 0 | K9: =MAX(0,C9+E9-D9-B9) -> 0 | L9: =F9*LaborCost -> 44800 | M9: =K9*HoldCost -> 0 | N9: =J9*BackorderCost -> 0 | O9: =H9*HireCost -> 0 | P9: =I9*LayoffCost -> 4500 | Q9: =L9+O9+P9+M9+N9 -> 49300
A10: September | B10: 10500 | C10: =K9 -> 0 | D10: =J9 -> 0 | E10: =MAX(0,B10+$C$18-C10+D10) -> 10500 | F10: =ROUNDUP(E10/$C$17,0) -> 11 | G10: =F10*$C$17 -> 11000 | H10: =MAX(0,F10-F9) -> 0 | I10: =MAX(0,F9-F10) -> 3 | J10: =MAX(0,B10+D10-C10-E10) -> 0 | K10: =MAX(0,C10+E10-D10-B10) -> 0 | L10: =F10*LaborCost -> 35200 | M10: =K10*HoldCost -> 0 | N10: =J10*BackorderCost -> 0 | O10: =H10*HireCost -> 0 | P10: =I10*LayoffCost -> 2700 | Q10: =L10+O10+P10+M10+N10 -> 37900
A11: October | B11: 9000 | C11: =K10 -> 0 | D11: =J10 -> 0 | E11: =MAX(0,B11+$C$18-C11+D11) -> 9000 | F11: =ROUNDUP(E11/$C$17,0) -> 9 | G11: =F11*$C$17 -> 9000 | H11: =MAX(0,F11-F10) -> 0 | I11: =MAX(0,F10-F11) -> 2 | J11: =MAX(0,B11+D11-C11-E11) -> 0 | K11: =MAX(0,C11+E11-D11-B11) -> 0 | L11: =F11*LaborCost -> 28800 | M11: =K11*HoldCost -> 0 | N11: =J11*BackorderCost -> 0 | O11: =H11*HireCost -> 0 | P11: =I11*LayoffCost -> 1800 | Q11: =L11+O11+P11+M11+N11 -> 30600
A12: November | B12: 7000 | C12: =K11 -> 0 | D12: =J11 -> 0 | E12: =MAX(0,B12+$C$18-C12+D12) -> 7000 | F12: =ROUNDUP(E12/$C$17,0) -> 7 | G12: =F12*$C$17 -> 7000 | H12: =MAX(0,F12-F11) -> 0 | I12: =MAX(0,F11-F12) -> 2 | J12: =MAX(0,B12+D12-C12-E12) -> 0 | K12: =MAX(0,C12+E12-D12-B12) -> 0 | L12: =F12*LaborCost -> 22400 | M12: =K12*HoldCost -> 0 | N12: =J12*BackorderCost -> 0 | O12: =H12*HireCost -> 0 | P12: =I12*LayoffCost -> 1800 | Q12: =L12+O12+P12+M12+N12 -> 24200
A13: December | B13: 6000 | C13: =K12 -> 0 | D13: =J12 -> 0 | E13: =MAX(0,B13+$C$18-C13+D13) -> 6000 | F13: =ROUNDUP(E13/$C$17,0) -> 6 | G13: =F13*$C$17 -> 6000 | H13: =MAX(0,F13-F12) -> 0 | I13: =MAX(0,F12-F13) -> 1 | J13: =MAX(0,B13+D13-C13-E13) -> 0 | K13: =MAX(0,C13+E13-D13-B13) -> 0 | L13: =F13*LaborCost -> 19200 | M13: =K13*HoldCost -> 0 | N13: =J13*BackorderCost -> 0 | O13: =H13*HireCost -> 0 | P13: =I13*LayoffCost -> 900 | Q13: =L13+O13+P13+M13+N13 -> 20100
A14: Year total | E14: =SUM(E2:E13) -> 123600 | G14: =SUM(G2:G13) -> 126000 | H14: =SUM(H2:H13) -> 14 | I14: =SUM(I2:I13) -> 16 | L14: =SUM(L2:L13) -> 403200 | M14: =SUM(M2:M13) -> 0 | N14: =SUM(N2:N13) -> 0 | O14: =SUM(O2:O13) -> 8400 | P14: =SUM(P2:P13) -> 14400 | Q14: =SUM(Q2:Q13) -> 426000
A16: Planning calculations — do these first
A17: Capacity per worker (bottles/worker/month) | C17: =BottlesPerHour*HoursPerDay*DaysPerMonth -> 1000
A18: Ending inventory target (bottles) | C18: =EndTarget -> 0
A20: CHASE PLAN — change the workforce every month so production follows demand.
A21: Row 1: your headings. Rows 2–13: your formulas for January–December. Row 14: yearly totals. Add helper columns if they help you think.

Sheet Level Plan
A1: Month | B1: Demand | C1: Beginning Inventory | D1: Beginning Backorders | E1: Production | F1: Workers | G1: Hires | H1: Layoffs | I1: Ending Inventory | J1: Ending Backorders | K1: Labor Cost | L1: Hiring Cost | M1: Layoff Cost | N1: Holding Cost | O1: Backorder Cost | P1: Total Cost
A2: January | B2: 7000 | C2: =BeginInv -> 2400 | D2: =0 -> 0 | E2: =$C$20 -> 10300 | F2: =$C$21 -> 11 | G2: =MAX(0,F2-StartWorkers) -> 3 | H2: =MAX(0,StartWorkers-F2) -> 0 | I2: =MAX(0,C2+E2-D2-B2) -> 5700 | J2: =MAX(0,B2+D2-C2-E2) -> 0 | K2: =F2*LaborCost -> 35200 | L2: =G2*HireCost -> 1800 | M2: =H2*LayoffCost -> 0 | N2: =I2*HoldCost -> 1425 | O2: =J2*BackorderCost -> 0 | P2: =K2+L2+M2+N2+O2 -> 38425
A3: February | B3: 6000 | C3: =I2 -> 5700 | D3: =J2 -> 0 | E3: =$C$20 -> 10300 | F3: =$C$21 -> 11 | G3: =MAX(0,F3-F2) -> 0 | H3: =MAX(0,F2-F3) -> 0 | I3: =MAX(0,C3+E3-D3-B3) -> 10000 | J3: =MAX(0,B3+D3-C3-E3) -> 0 | K3: =F3*LaborCost -> 35200 | L3: =G3*HireCost -> 0 | M3: =H3*LayoffCost -> 0 | N3: =I3*HoldCost -> 2500 | O3: =J3*BackorderCost -> 0 | P3: =K3+L3+M3+N3+O3 -> 37700
A4: March | B4: 7000 | C4: =I3 -> 10000 | D4: =J3 -> 0 | E4: =$C$20 -> 10300 | F4: =$C$21 -> 11 | G4: =MAX(0,F4-F3) -> 0 | H4: =MAX(0,F3-F4) -> 0 | I4: =MAX(0,C4+E4-D4-B4) -> 13300 | J4: =MAX(0,B4+D4-C4-E4) -> 0 | K4: =F4*LaborCost -> 35200 | L4: =G4*HireCost -> 0 | M4: =H4*LayoffCost -> 0 | N4: =I4*HoldCost -> 3325 | O4: =J4*BackorderCost -> 0 | P4: =K4+L4+M4+N4+O4 -> 38525
A5: April | B5: 11500 | C5: =I4 -> 13300 | D5: =J4 -> 0 | E5: =$C$20 -> 10300 | F5: =$C$21 -> 11 | G5: =MAX(0,F5-F4) -> 0 | H5: =MAX(0,F4-F5) -> 0 | I5: =MAX(0,C5+E5-D5-B5) -> 12100 | J5: =MAX(0,B5+D5-C5-E5) -> 0 | K5: =F5*LaborCost -> 35200 | L5: =G5*HireCost -> 0 | M5: =H5*LayoffCost -> 0 | N5: =I5*HoldCost -> 3025 | O5: =J5*BackorderCost -> 0 | P5: =K5+L5+M5+N5+O5 -> 38225
A6: May | B6: 13000 | C6: =I5 -> 12100 | D6: =J5 -> 0 | E6: =$C$20 -> 10300 | F6: =$C$21 -> 11 | G6: =MAX(0,F6-F5) -> 0 | H6: =MAX(0,F5-F6) -> 0 | I6: =MAX(0,C6+E6-D6-B6) -> 9400 | J6: =MAX(0,B6+D6-C6-E6) -> 0 | K6: =F6*LaborCost -> 35200 | L6: =G6*HireCost -> 0 | M6: =H6*LayoffCost -> 0 | N6: =I6*HoldCost -> 2350 | O6: =J6*BackorderCost -> 0 | P6: =K6+L6+M6+N6+O6 -> 37550
A7: June | B7: 16500 | C7: =I6 -> 9400 | D7: =J6 -> 0 | E7: =$C$20 -> 10300 | F7: =$C$21 -> 11 | G7: =MAX(0,F7-F6) -> 0 | H7: =MAX(0,F6-F7) -> 0 | I7: =MAX(0,C7+E7-D7-B7) -> 3200 | J7: =MAX(0,B7+D7-C7-E7) -> 0 | K7: =F7*LaborCost -> 35200 | L7: =G7*HireCost -> 0 | M7: =H7*LayoffCost -> 0 | N7: =I7*HoldCost -> 800 | O7: =J7*BackorderCost -> 0 | P7: =K7+L7+M7+N7+O7 -> 36000
A8: July | B8: 18500 | C8: =I7 -> 3200 | D8: =J7 -> 0 | E8: =$C$20 -> 10300 | F8: =$C$21 -> 11 | G8: =MAX(0,F8-F7) -> 0 | H8: =MAX(0,F7-F8) -> 0 | I8: =MAX(0,C8+E8-D8-B8) -> 0 | J8: =MAX(0,B8+D8-C8-E8) -> 5000 | K8: =F8*LaborCost -> 35200 | L8: =G8*HireCost -> 0 | M8: =H8*LayoffCost -> 0 | N8: =I8*HoldCost -> 0 | O8: =J8*BackorderCost -> 7500 | P8: =K8+L8+M8+N8+O8 -> 42700
A9: August | B9: 14000 | C9: =I8 -> 0 | D9: =J8 -> 5000 | E9: =$C$20 -> 10300 | F9: =$C$21 -> 11 | G9: =MAX(0,F9-F8) -> 0 | H9: =MAX(0,F8-F9) -> 0 | I9: =MAX(0,C9+E9-D9-B9) -> 0 | J9: =MAX(0,B9+D9-C9-E9) -> 8700 | K9: =F9*LaborCost -> 35200 | L9: =G9*HireCost -> 0 | M9: =H9*LayoffCost -> 0 | N9: =I9*HoldCost -> 0 | O9: =J9*BackorderCost -> 13050 | P9: =K9+L9+M9+N9+O9 -> 48250
A10: September | B10: 10500 | C10: =I9 -> 0 | D10: =J9 -> 8700 | E10: =$C$20 -> 10300 | F10: =$C$21 -> 11 | G10: =MAX(0,F10-F9) -> 0 | H10: =MAX(0,F9-F10) -> 0 | I10: =MAX(0,C10+E10-D10-B10) -> 0 | J10: =MAX(0,B10+D10-C10-E10) -> 8900 | K10: =F10*LaborCost -> 35200 | L10: =G10*HireCost -> 0 | M10: =H10*LayoffCost -> 0 | N10: =I10*HoldCost -> 0 | O10: =J10*BackorderCost -> 13350 | P10: =K10+L10+M10+N10+O10 -> 48550
A11: October | B11: 9000 | C11: =I10 -> 0 | D11: =J10 -> 8900 | E11: =$C$20 -> 10300 | F11: =$C$21 -> 11 | G11: =MAX(0,F11-F10) -> 0 | H11: =MAX(0,F10-F11) -> 0 | I11: =MAX(0,C11+E11-D11-B11) -> 0 | J11: =MAX(0,B11+D11-C11-E11) -> 7600 | K11: =F11*LaborCost -> 35200 | L11: =G11*HireCost -> 0 | M11: =H11*LayoffCost -> 0 | N11: =I11*HoldCost -> 0 | O11: =J11*BackorderCost -> 11400 | P11: =K11+L11+M11+N11+O11 -> 46600
A12: November | B12: 7000 | C12: =I11 -> 0 | D12: =J11 -> 7600 | E12: =$C$20 -> 10300 | F12: =$C$21 -> 11 | G12: =MAX(0,F12-F11) -> 0 | H12: =MAX(0,F11-F12) -> 0 | I12: =MAX(0,C12+E12-D12-B12) -> 0 | J12: =MAX(0,B12+D12-C12-E12) -> 4300 | K12: =F12*LaborCost -> 35200 | L12: =G12*HireCost -> 0 | M12: =H12*LayoffCost -> 0 | N12: =I12*HoldCost -> 0 | O12: =J12*BackorderCost -> 6450 | P12: =K12+L12+M12+N12+O12 -> 41650
A13: December | B13: 6000 | C13: =I12 -> 0 | D13: =J12 -> 4300 | E13: =$C$20 -> 10300 | F13: =$C$21 -> 11 | G13: =MAX(0,F13-F12) -> 0 | H13: =MAX(0,F12-F13) -> 0 | I13: =MAX(0,C13+E13-D13-B13) -> 0 | J13: =MAX(0,B13+D13-C13-E13) -> 0 | K13: =F13*LaborCost -> 35200 | L13: =G13*HireCost -> 0 | M13: =H13*LayoffCost -> 0 | N13: =I13*HoldCost -> 0 | O13: =J13*BackorderCost -> 0 | P13: =K13+L13+M13+N13+O13 -> 35200
A14: Year total | E14: =SUM(E2:E13) -> 123600 | G14: =SUM(G2:G13) -> 3 | H14: =SUM(H2:H13) -> 0 | K14: =SUM(K2:K13) -> 422400 | L14: =SUM(L2:L13) -> 1800 | M14: =SUM(M2:M13) -> 0 | N14: =SUM(N2:N13) -> 13425 | O14: =SUM(O2:O13) -> 51750 | P14: =SUM(P2:P13) -> 489375
A16: Planning calculations — do these first
A17: Capacity per worker (bottles/worker/month) | C17: =BottlesPerHour*HoursPerDay*DaysPerMonth -> 1000
A18: Ending inventory target for December (bottles) | C18: =EndTarget -> 0
A19: Total annual demand (bottles) | C19: =SUM(B2:B13) -> 126000
A20: Level production per month (bottles/month) | C20: =(C19+C18-BeginInv)/12 -> 10300
A21: Level workforce (workers) | C21: =ROUNDUP(C20/C17,0) -> 11
A23: LEVEL PLAN — one steady production rate and workforce all year.
A24: Row 1: your headings. Rows 2–13: your formulas for January–December. Row 14: yearly totals. Add helper columns if they help you think.

Sheet Hybrid Plan
A1: Month | B1: Demand | C1: Beginning Inventory | D1: Beginning Backorders | E1: Workers | F1: Regular Capacity | G1: Regular Production | H1: Overtime Production | I1: Subcontract Production | J1: Total Production | K1: Hires | L1: Layoffs | M1: Ending Inventory | N1: Ending Backorders | O1: Labor Cost | P1: Hiring Cost | Q1: Layoff Cost | R1: Overtime Cost | S1: Subcontract Cost | T1: Holding Cost | U1: Backorder Cost | V1: Total Cost
A2: January | B2: 7000 | C2: =BeginInv -> 2400 | D2: =0 -> 0 | E2: 11 | F2: =E2*$C$17 -> 11000 | G2: 11000 | H2: 0 | I2: 0 | J2: =G2+H2+I2 -> 11000 | K2: =MAX(0,E2-StartWorkers) -> 3 | L2: =MAX(0,StartWorkers-E2) -> 0 | M2: =MAX(0,C2+J2-D2-B2) -> 6400 | N2: =MAX(0,B2+D2-C2-J2) -> 0 | O2: =E2*LaborCost -> 35200 | P2: =K2*HireCost -> 1800 | Q2: =L2*LayoffCost -> 0 | R2: =H2*OTCost -> 0 | S2: =I2*SubCost -> 0 | T2: =M2*HoldCost -> 1600 | U2: =N2*BackorderCost -> 0 | V2: =O2+P2+Q2+R2+S2+T2+U2 -> 38600
A3: February | B3: 6000 | C3: =M2 -> 6400 | D3: =N2 -> 0 | E3: 11 | F3: =E3*$C$17 -> 11000 | G3: 11000 | H3: 0 | I3: 0 | J3: =G3+H3+I3 -> 11000 | K3: =MAX(0,E3-E2) -> 0 | L3: =MAX(0,E2-E3) -> 0 | M3: =MAX(0,C3+J3-D3-B3) -> 11400 | N3: =MAX(0,B3+D3-C3-J3) -> 0 | O3: =E3*LaborCost -> 35200 | P3: =K3*HireCost -> 0 | Q3: =L3*LayoffCost -> 0 | R3: =H3*OTCost -> 0 | S3: =I3*SubCost -> 0 | T3: =M3*HoldCost -> 2850 | U3: =N3*BackorderCost -> 0 | V3: =O3+P3+Q3+R3+S3+T3+U3 -> 38050
A4: March | B4: 7000 | C4: =M3 -> 11400 | D4: =N3 -> 0 | E4: 11 | F4: =E4*$C$17 -> 11000 | G4: 11000 | H4: 0 | I4: 0 | J4: =G4+H4+I4 -> 11000 | K4: =MAX(0,E4-E3) -> 0 | L4: =MAX(0,E3-E4) -> 0 | M4: =MAX(0,C4+J4-D4-B4) -> 15400 | N4: =MAX(0,B4+D4-C4-J4) -> 0 | O4: =E4*LaborCost -> 35200 | P4: =K4*HireCost -> 0 | Q4: =L4*LayoffCost -> 0 | R4: =H4*OTCost -> 0 | S4: =I4*SubCost -> 0 | T4: =M4*HoldCost -> 3850 | U4: =N4*BackorderCost -> 0 | V4: =O4+P4+Q4+R4+S4+T4+U4 -> 39050
A5: April | B5: 11500 | C5: =M4 -> 15400 | D5: =N4 -> 0 | E5: 11 | F5: =E5*$C$17 -> 11000 | G5: 11000 | H5: 0 | I5: 0 | J5: =G5+H5+I5 -> 11000 | K5: =MAX(0,E5-E4) -> 0 | L5: =MAX(0,E4-E5) -> 0 | M5: =MAX(0,C5+J5-D5-B5) -> 14900 | N5: =MAX(0,B5+D5-C5-J5) -> 0 | O5: =E5*LaborCost -> 35200 | P5: =K5*HireCost -> 0 | Q5: =L5*LayoffCost -> 0 | R5: =H5*OTCost -> 0 | S5: =I5*SubCost -> 0 | T5: =M5*HoldCost -> 3725 | U5: =N5*BackorderCost -> 0 | V5: =O5+P5+Q5+R5+S5+T5+U5 -> 38925
A6: May | B6: 13000 | C6: =M5 -> 14900 | D6: =N5 -> 0 | E6: 11 | F6: =E6*$C$17 -> 11000 | G6: 11000 | H6: 0 | I6: 0 | J6: =G6+H6+I6 -> 11000 | K6: =MAX(0,E6-E5) -> 0 | L6: =MAX(0,E5-E6) -> 0 | M6: =MAX(0,C6+J6-D6-B6) -> 12900 | N6: =MAX(0,B6+D6-C6-J6) -> 0 | O6: =E6*LaborCost -> 35200 | P6: =K6*HireCost -> 0 | Q6: =L6*LayoffCost -> 0 | R6: =H6*OTCost -> 0 | S6: =I6*SubCost -> 0 | T6: =M6*HoldCost -> 3225 | U6: =N6*BackorderCost -> 0 | V6: =O6+P6+Q6+R6+S6+T6+U6 -> 38425
A7: June | B7: 16500 | C7: =M6 -> 12900 | D7: =N6 -> 0 | E7: 11 | F7: =E7*$C$17 -> 11000 | G7: 11000 | H7: 1000 | I7: 0 | J7: =G7+H7+I7 -> 12000 | K7: =MAX(0,E7-E6) -> 0 | L7: =MAX(0,E6-E7) -> 0 | M7: =MAX(0,C7+J7-D7-B7) -> 8400 | N7: =MAX(0,B7+D7-C7-J7) -> 0 | O7: =E7*LaborCost -> 35200 | P7: =K7*HireCost -> 0 | Q7: =L7*LayoffCost -> 0 | R7: =H7*OTCost -> 4500 | S7: =I7*SubCost -> 0 | T7: =M7*HoldCost -> 2100 | U7: =N7*BackorderCost -> 0 | V7: =O7+P7+Q7+R7+S7+T7+U7 -> 41800
A8: July | B8: 18500 | C8: =M7 -> 8400 | D8: =N7 -> 0 | E8: 11 | F8: =E8*$C$17 -> 11000 | G8: 11000 | H8: 2000 | I8: 0 | J8: =G8+H8+I8 -> 13000 | K8: =MAX(0,E8-E7) -> 0 | L8: =MAX(0,E7-E8) -> 0 | M8: =MAX(0,C8+J8-D8-B8) -> 2900 | N8: =MAX(0,B8+D8-C8-J8) -> 0 | O8: =E8*LaborCost -> 35200 | P8: =K8*HireCost -> 0 | Q8: =L8*LayoffCost -> 0 | R8: =H8*OTCost -> 9000 | S8: =I8*SubCost -> 0 | T8: =M8*HoldCost -> 725 | U8: =N8*BackorderCost -> 0 | V8: =O8+P8+Q8+R8+S8+T8+U8 -> 44925
A9: August | B9: 14000 | C9: =M8 -> 2900 | D9: =N8 -> 0 | E9: 11 | F9: =E9*$C$17 -> 11000 | G9: 11000 | H9: 0 | I9: 0 | J9: =G9+H9+I9 -> 11000 | K9: =MAX(0,E9-E8) -> 0 | L9: =MAX(0,E8-E9) -> 0 | M9: =MAX(0,C9+J9-D9-B9) -> 0 | N9: =MAX(0,B9+D9-C9-J9) -> 100 | O9: =E9*LaborCost -> 35200 | P9: =K9*HireCost -> 0 | Q9: =L9*LayoffCost -> 0 | R9: =H9*OTCost -> 0 | S9: =I9*SubCost -> 0 | T9: =M9*HoldCost -> 0 | U9: =N9*BackorderCost -> 150 | V9: =O9+P9+Q9+R9+S9+T9+U9 -> 35350
A10: September | B10: 10500 | C10: =M9 -> 0 | D10: =N9 -> 100 | E10: 11 | F10: =E10*$C$17 -> 11000 | G10: 11000 | H10: 0 | I10: 0 | J10: =G10+H10+I10 -> 11000 | K10: =MAX(0,E10-E9) -> 0 | L10: =MAX(0,E9-E10) -> 0 | M10: =MAX(0,C10+J10-D10-B10) -> 400 | N10: =MAX(0,B10+D10-C10-J10) -> 0 | O10: =E10*LaborCost -> 35200 | P10: =K10*HireCost -> 0 | Q10: =L10*LayoffCost -> 0 | R10: =H10*OTCost -> 0 | S10: =I10*SubCost -> 0 | T10: =M10*HoldCost -> 100 | U10: =N10*BackorderCost -> 0 | V10: =O10+P10+Q10+R10+S10+T10+U10 -> 35300
A11: October | B11: 9000 | C11: =M10 -> 400 | D11: =N10 -> 0 | E11: 11 | F11: =E11*$C$17 -> 11000 | G11: 11000 | H11: 0 | I11: 0 | J11: =G11+H11+I11 -> 11000 | K11: =MAX(0,E11-E10) -> 0 | L11: =MAX(0,E10-E11) -> 0 | M11: =MAX(0,C11+J11-D11-B11) -> 2400 | N11: =MAX(0,B11+D11-C11-J11) -> 0 | O11: =E11*LaborCost -> 35200 | P11: =K11*HireCost -> 0 | Q11: =L11*LayoffCost -> 0 | R11: =H11*OTCost -> 0 | S11: =I11*SubCost -> 0 | T11: =M11*HoldCost -> 600 | U11: =N11*BackorderCost -> 0 | V11: =O11+P11+Q11+R11+S11+T11+U11 -> 35800
A12: November | B12: 7000 | C12: =M11 -> 2400 | D12: =N11 -> 0 | E12: 11 | F12: =E12*$C$17 -> 11000 | G12: 11000 | H12: 0 | I12: 0 | J12: =G12+H12+I12 -> 11000 | K12: =MAX(0,E12-E11) -> 0 | L12: =MAX(0,E11-E12) -> 0 | M12: =MAX(0,C12+J12-D12-B12) -> 6400 | N12: =MAX(0,B12+D12-C12-J12) -> 0 | O12: =E12*LaborCost -> 35200 | P12: =K12*HireCost -> 0 | Q12: =L12*LayoffCost -> 0 | R12: =H12*OTCost -> 0 | S12: =I12*SubCost -> 0 | T12: =M12*HoldCost -> 1600 | U12: =N12*BackorderCost -> 0 | V12: =O12+P12+Q12+R12+S12+T12+U12 -> 36800
A13: December | B13: 6000 | C13: =M12 -> 6400 | D13: =N12 -> 0 | E13: 11 | F13: =E13*$C$17 -> 11000 | G13: 11000 | H13: 0 | I13: 0 | J13: =G13+H13+I13 -> 11000 | K13: =MAX(0,E13-E12) -> 0 | L13: =MAX(0,E12-E13) -> 0 | M13: =MAX(0,C13+J13-D13-B13) -> 11400 | N13: =MAX(0,B13+D13-C13-J13) -> 0 | O13: =E13*LaborCost -> 35200 | P13: =K13*HireCost -> 0 | Q13: =L13*LayoffCost -> 0 | R13: =H13*OTCost -> 0 | S13: =I13*SubCost -> 0 | T13: =M13*HoldCost -> 2850 | U13: =N13*BackorderCost -> 0 | V13: =O13+P13+Q13+R13+S13+T13+U13 -> 38050
A14: Year total | F14: =SUM(F2:F13) -> 132000 | G14: =SUM(G2:G13) -> 132000 | H14: =SUM(H2:H13) -> 3000 | I14: =SUM(I2:I13) -> 0 | J14: =SUM(J2:J13) -> 135000 | K14: =SUM(K2:K13) -> 3 | L14: =SUM(L2:L13) -> 0 | O14: =SUM(O2:O13) -> 422400 | P14: =SUM(P2:P13) -> 1800 | Q14: =SUM(Q2:Q13) -> 0 | R14: =SUM(R2:R13) -> 13500 | S14: =SUM(S2:S13) -> 0 | T14: =SUM(T2:T13) -> 23225 | U14: =SUM(U2:U13) -> 150 | V14: =SUM(V2:V13) -> 461075
A16: Planning calculations — do these first
A17: Capacity per worker (bottles/worker/month) | C17: =BottlesPerHour*HoursPerDay*DaysPerMonth -> 1000
A18: Overtime limit per worker (bottles/worker/month) | C18: =C17*OTLimitPct -> 200
A20: HYBRID PLAN — your own strategy: choose workers, regular production, overtime and subcontracting each month, then calculate the results.
A21: Row 1: your headings. Rows 2–13: your formulas for January–December. Row 14: yearly totals. Add helper columns if they help you think.
A22: Limits: overtime only once regular capacity is full and at most OTLimitPct of it; subcontracting at most SubCapacity; inventory at most MaxInventory; no backorders left in December; December inventory at least EndTarget.

Sheet Summary
A1: Summary: compare the plans and recommend one
A3: Measure | B3: Chase | C3: Level | D3: Hybrid | E3: Where it comes from
A4: Total labor cost | B4: ='Chase Plan'!L14 -> 403200 | C4: ='Level Plan'!K14 -> 422400 | D4: ='Hybrid Plan'!O14 -> 422400 | E4: from the plan's yearly totals
A5: Total hiring cost | B5: ='Chase Plan'!O14 -> 8400 | C5: ='Level Plan'!L14 -> 1800 | D5: ='Hybrid Plan'!P14 -> 1800 | E5: from the plan's yearly totals
A6: Total layoff cost | B6: ='Chase Plan'!P14 -> 14400 | C6: ='Level Plan'!M14 -> 0 | D6: ='Hybrid Plan'!Q14 -> 0 | E6: from the plan's yearly totals
A7: Total overtime cost | B7: n/a | C7: n/a | D7: ='Hybrid Plan'!R14 -> 13500 | E7: hybrid only
A8: Total subcontract cost | B8: n/a | C8: n/a | D8: ='Hybrid Plan'!S14 -> 0 | E8: hybrid only
A9: Total holding cost | B9: ='Chase Plan'!M14 -> 0 | C9: ='Level Plan'!N14 -> 13425 | D9: ='Hybrid Plan'!T14 -> 23225 | E9: from the plan's yearly totals
A10: Total backorder cost | B10: ='Chase Plan'!N14 -> 0 | C10: ='Level Plan'!O14 -> 51750 | D10: ='Hybrid Plan'!U14 -> 150 | E10: from the plan's yearly totals
A11: TOTAL PLAN COST | B11: ='Chase Plan'!Q14 -> 426000 | C11: ='Level Plan'!P14 -> 489375 | D11: ='Hybrid Plan'!V14 -> 461075 | E11: from the plan's yearly totals
A12: Total workers hired | B12: ='Chase Plan'!H14 -> 14 | C12: ='Level Plan'!G14 -> 3 | D12: ='Hybrid Plan'!K14 -> 3 | E12: over the whole year
A13: Total workers laid off | B13: ='Chase Plan'!I14 -> 16 | C13: ='Level Plan'!H14 -> 0 | D13: ='Hybrid Plan'!L14 -> 0 | E13: over the whole year
A14: Largest workforce | B14: =MAX('Chase Plan'!F2:F13) -> 19 | C14: =MAX('Level Plan'!F2:F13) -> 11 | D14: =MAX('Hybrid Plan'!E2:E13) -> 11 | E14: the biggest month
A15: Largest ending inventory (storage needed) | B15: =MAX('Chase Plan'!K2:K13) -> 0 | C15: =MAX('Level Plan'!I2:I13) -> 13300 | D15: =MAX('Hybrid Plan'!M2:M13) -> 15400 | E15: the biggest month
A16: Months ending with backorders | B16: =COUNTIF('Chase Plan'!J2:J13,">0") -> 0 | C16: =COUNTIF('Level Plan'!J2:J13,">0") -> 5 | D16: =COUNTIF('Hybrid Plan'!N2:N13,">0") -> 1 | E16: a count of months
A18: Lower-cost plan: Chase or Level? | B18: =IF(B11<C11,"Chase","Level") -> Chase | E18: let Excel decide with a formula
A19: Savings of the lower-cost plan ($) | B19: =ABS(B11-C11) -> 63375 | E19: a positive number
A21: Your recommendation | B21: Chase | E21: pick from the drop-down list
A22: Why? Justify it in your own words. | B22: ANSWER KEY. The recommendation and its justification are the student's own judgement and are graded by the instructor, not by the checker. ANSWER KEY. The recommendation and its justification are the student's own judgement and are graded by the instructor, not by the checker. ANSWER KEY. The recommendation and its justification are the student's own judgement and are graded by the instructor, not by the checker.
A23: At least 50 words. Use your numbers: cost, workforce changes, inventory, backorders, and the risks your plan takes.

Sheet Excel Help
A1: Excel help
A3: Habits that make this easy
A4: Start every calculation with = | B4: Type =C2+E2 rather than the number you worked out. The checker wants formulas, because a formula updates itself when an input changes.
A5: Fill down | B5: Write February's formula once, select it and drag the small square at the bottom-right corner down to December (or double-click it).
A6: Absolute references with $ | B6: When every month must point at ONE cell (for example a planning cell such as $C$17), lock it with $ signs or use a name. Without the $, filling down slides the reference onto empty cells.
A7: Use the names | B7: Every given number has a name (LaborCost, HireCost, BeginInv, ...). =F2*LaborCost is easier to read and check than =F2*Scenario!$B$22.
A8: Link, don't retype | B8: On the Summary sheet, point at your plan's totals: type = and click the total on the plan sheet. If your plan changes, the summary follows.
A9: Save, then upload | B9: Save the file as .xlsx in Excel (or Google Sheets → Download → .xlsx) so the calculated values are stored. Then upload it in the app.
A11: Functions you may need
A12: SUM | B12: =SUM(B2:B13) | C12: adds a range of cells
A13: MAX | B13: =MAX(0, A5-B5) | C13: the larger value: with 0 first, a result can never go below zero
A14: MIN | B14: =MIN(B2:B13) | C14: the smallest value
A15: ROUNDUP | B15: =ROUNDUP(7.2, 0) | C15: rounds up to a whole number: 7.2 becomes 8
A16: IF | B16: =IF(A1<B1,"A","B") | C16: picks one of two results based on a test
A17: COUNTIF | B17: =COUNTIF(A2:A13,">0") | C17: counts the cells that meet a condition
A18: ABS | B18: =ABS(A1-B1) | C18: size of a difference, without the minus sign
A20: What an error means
A21: #DIV/0! | B21: you divided by zero or by an empty cell — check what is right of the /
A22: #NAME? | B22: Excel does not know a word in the formula — check the spelling of a name or function (ROUNDUP, LaborCost)
A23: #REF! | B23: the formula points at a cell that was deleted — undo (Ctrl+Z) and retype
A24: #VALUE! | B24: text where a number was expected — a cell holds words or a stray space
A25: #### | B25: not an error: the column is too narrow; widen it
A27: Practice: absolute references
A28: Cost = bottles × the ONE rate in B30. Type a formula in C31 and fill it down. Without a $ sign the rows below show 0 — that is the lesson.
A30: Rate ($/bottle) | B30: 0.25
A31: Month 1 | B31: 1200
A32: Month 2 | B32: 850
A33: Month 3 | B33: 1500
A34: Month 4 | B34: 2300
A35: Month 5 | B35: 975
A36: Month 6 | B36: 1840

Sheet _meta
A1: app | B1: aggregate-anxiety-excel
A2: schema | B2: 2
A3: model_version | B3: 5.0.0
A4: seed | B4: 7
A5: config_hash | B5: fdf36332bcdfa8fc
A6: student_id | B6: S1
A7: student_name | B7: Test Student
A8: game
A9: created_utc | B9: 2026-10-19T18:53:57Z
A10: workbook_id | B10: 3c31afe24ae8
